fastsetup/__init__.py
fastsetup/orchestrator_api.py
fastsetup/tools.py
fastsetup-1.0.0.dist-info/LICENSE
fastsetup-1.0.0.dist-info/METADATA
fastsetup-1.0.0.dist-info/WHEEL
fastsetup-1.0.0.dist-info/top_level.txt
fastsetup-1.0.0.dist-info/RECORD
